sprockets.mixins.amqp-2.2.0-py3.7-nspkg.pth
sprockets/mixins/amqp/__init__.py
tests/__init__.py
tests/base.py
tests/client_tests.py
tests/install_tests.py
tests/integration_tests.py
tests/mixin_tests.py
sprockets.mixins.amqp-2.2.0.dist-info/LICENSE
sprockets.mixins.amqp-2.2.0.dist-info/METADATA
sprockets.mixins.amqp-2.2.0.dist-info/WHEEL
sprockets.mixins.amqp-2.2.0.dist-info/namespace_packages.txt
sprockets.mixins.amqp-2.2.0.dist-info/top_level.txt
sprockets.mixins.amqp-2.2.0.dist-info/zip-safe
sprockets.mixins.amqp-2.2.0.dist-info/RECORD
