Metadata-Version: 2.1
Name: sprockets.mixins.amqp
Version: 2.2.0
Summary: Mixin for publishing events to RabbitMQ
Home-page: https://github.com/sprockets/sprockets.mixins.amqp
Author: AWeber Communications, Inc.
Author-email: api@aweber.com
License: BSD
Platform: UNKNOWN
Classifier: Development Status :: 4 - Beta
Classifier: Intended Audience :: Developers
Classifier: License :: OSI Approved :: BSD License
Classifier: Natural Language :: English
Classifier: Operating System :: OS Independent
Classifier: Programming Language :: Python :: 3
Classifier: Programming Language :: Python :: 3.5
Classifier: Programming Language :: Python :: 3.6
Classifier: Programming Language :: Python :: 3.7
Classifier: Programming Language :: Python :: Implementation :: CPython
Classifier: Programming Language :: Python :: Implementation :: PyPy
Classifier: Topic :: Software Development :: Libraries
Classifier: Topic :: Software Development :: Libraries :: Python Modules
Requires-Dist: pika (==0.12.0)
Requires-Dist: tornado (<6,>=4.2.0)
